[
    {
        "Meta-analysis results for mean daily step count reported.": {
            "Wearable Tech": [
                "Arbillaga-Etxarri et al., 2018",
                "Armstrong et al., 2021",
                "Benzo et al., 2021",
                "Chen et al., 2022",
                "de Blok et al., 2006",
                "Demeyer et al., 2017",
                "Geidl et al., 2021",
                "Hornikx et al., 2015",
                "Hospes et al., 2009",
                "Kohlbrenner et al., 2020",
                "Mendoza et al., 2015",
                "Nguyen et al., 2009",
                "Nolan et al., 2017",
                "Park et al., 2020",
                "Robinson et al., 2021",
                "Valeiro et al., 2023",
                "Varas et al., 2018",
                "Vorrink et al., 2016",
                "Wan et al., 2017",
                "Wootton et al., 2019"
            ]
        }
    },
    {
        "Meta-analysis results for the six-minute walk distance (m).": {
            "Wearable Tech": [
                "Arbillaga-Etxarri et al., 2018",
                "Armstrong et al., 2021",
                "Chen et al., 2022",
                "Demeyer et al., 2017",
                "Hornikx et al., 2015",
                "Hospes et al., 2009",
                "Kato et al., 2017",
                "Kawagoshi et al., 2015",
                "Mendoza et al., 2015",
                "Nguyen et al., 2009",
                "Park et al., 2020",
                "Robinson et al., 2021",
                "Valeiro et al., 2023",
                "Vorrink et al., 2016",
                "Wan et al., 2017",
                "Wootton et al., 2018"
            ]
        }
    },
    {
        "Meta-analysis results for the COPD Assessment Tool score.": {
            "Wearable Tech": [
                "Arbillaga-Etxarri et al., 2018",
                "Armstrong et al., 2021",
                "Chen et al., 2022",
                "Demeyer et al., 2017",
                "Geidl et al., 2021",
                "Kato et al., 2017",
                "Kohlbrenner et al., 2020",
                "Mendoza et al., 2015",
                "Spielmanns et al., 2023",
                "Valeiro et al., 2023",
                "Wootton et al., 2018"
            ]
        }
    },
    {
        "Meta-analysis investigating the association between wearable technology and COPD exacerbations.": {
            "Wearable Tech": [
                "Arbillaga-Etxarri et al., 2018",
                "Nguyen et al., 2019",
                "Park et al., 2020",
                "Robinson et al., 2021"
            ]
        }
    }
]